methodoverload/__init__.py
methodoverload/cache.py
methodoverload/core.py
methodoverload/decorators.py
methodoverload/errors.py
methodoverload/metaclass.py
methodoverload/typing.py
methodoverload/utils.py
methodoverload-0.1.7.dist-info/licenses/LICENSE
methodoverload-0.1.7.dist-info/METADATA
methodoverload-0.1.7.dist-info/WHEEL
methodoverload-0.1.7.dist-info/top_level.txt
methodoverload-0.1.7.dist-info/RECORD
