Metadata-Version: 2.4
Name: methodoverload
Version: 0.1.7
Summary: Runtime function and method overloading for Python
Home-page: https://github.com/mohdcodes/pyoverload
Author: Mohd Arbaaz Siddiqui
Author-email: Mohd Arbaaz Siddiqui <arbaazcode@gmail.com>
Maintainer-email: Mohd Arbaaz Siddiqui <arbaazcode@gmail.com>
License: MIT
Project-URL: Homepage, https://github.com/mohdcodes/pyoverload
Project-URL: Repository, https://github.com/mohdcodes/pyoverload.git
Project-URL: Documentation, https://github.com/mohdcodes/pyoverload/tree/main/methodoverload/docs
Project-URL: Issues, https://github.com/mohdcodes/pyoverload/tree/main/methodoverload/issues
Project-URL: Changelog, https://github.com/mohdcodes/pyoverload/releases
Project-URL: Features, https://github.com/mohdcodes/pyoverload/tree/main/methodoverload/features
Keywords: overloading,dispatch,typing,oop
Classifier: Programming Language :: Python :: 3
Classifier: Programming Language :: Python :: 3 :: Only
Classifier: Programming Language :: Python :: 3.9
Classifier: Programming Language :: Python :: 3.10
Classifier: Programming Language :: Python :: 3.11
Classifier: License :: OSI Approved :: MIT License
Classifier: Operating System :: OS Independent
Requires-Python: >=3.10
License-File: LICENSE
Provides-Extra: dev
Requires-Dist: pytest>=9.0; extra == "dev"
Requires-Dist: pytest-cov>=4.0; extra == "dev"
Provides-Extra: docs
Requires-Dist: sphinx>=6.0; extra == "docs"
Requires-Dist: sphinx-rtd-theme>=1.0; extra == "docs"
Dynamic: author
Dynamic: home-page
Dynamic: license-file
Dynamic: requires-python
